odoo/addons/website_event_track_stage_cancelled/README.rst
odoo/addons/website_event_track_stage_cancelled/__init__.py
odoo/addons/website_event_track_stage_cancelled/__manifest__.py
odoo/addons/website_event_track_stage_cancelled/i18n/it.po
odoo/addons/website_event_track_stage_cancelled/i18n/website_event_track_stage_cancelled.pot
odoo/addons/website_event_track_stage_cancelled/models/__init__.py
odoo/addons/website_event_track_stage_cancelled/models/event_event.py
odoo/addons/website_event_track_stage_cancelled/readme/CONFIGURE.md
odoo/addons/website_event_track_stage_cancelled/readme/CONTRIBUTORS.md
odoo/addons/website_event_track_stage_cancelled/readme/DESCRIPTION.md
odoo/addons/website_event_track_stage_cancelled/readme/USAGE.md
odoo/addons/website_event_track_stage_cancelled/static/description/icon.png
odoo/addons/website_event_track_stage_cancelled/static/description/index.html
odoo_addon_website_event_track_stage_cancelled-17.0.1.0.0.4.dist-info/METADATA
odoo_addon_website_event_track_stage_cancelled-17.0.1.0.0.4.dist-info/WHEEL
odoo_addon_website_event_track_stage_cancelled-17.0.1.0.0.4.dist-info/top_level.txt
odoo_addon_website_event_track_stage_cancelled-17.0.1.0.0.4.dist-info/RECORD
